{
  "type": "datasource",
  "name": "stevensli-plugin",
  "id": "tencentcloud-stevensli-plugin",
  "metrics": true,
  "info": {
    "description": "stevensli test plugin",
    "author": {
      "name": "keywoshilishuang",
      "url": "www.tencentcloud.com"
    },
    "keywords": [
      "test",
      "stevensli",
      "plugin"
    ],
    "logos": {
      "small": "img/logo.svg",
      "large": "img/logo.svg"
    },
    "links": [
      {
        "name": "Website",
        "url": "https://github.com/grafana/simple-datasource"
      },
      {
        "name": "License",
        "url": "https://github.com/grafana/simple-datasource/blob/master/LICENSE"
      }
    ],
    "screenshots": [],
    "version": "%VERSION%",
    "updated": "%TODAY%"
  },
  "dependencies": {
    "grafanaVersion": "6.5.x",
    "plugins": []
  }
}